{
	"data":[
	   {
		  "id":"1",
		  "created_at":"2023-02-02T16:05:56Z",
		  "updated_at":"2023-02-02T16:05:56Z",
		  "name":"/insights/platform/app-studio",
		  "display_name":"App Studio",
		  "dependent_applications":[

		  ],
		  "supported_source_types":[
			 "bitbucket",
			 "dockerhub",
			 "github",
			 "gitlab",
			 "quay"
		  ],
		  "supported_authentication_types":{
			 "quay":[
				"quay-encrypted-password"
			 ],
			 "github":[
				"github-personal-access-token"
			 ],
			 "gitlab":[
				"gitlab-personal-access-token"
			 ],
			 "bitbucket":[
				"bitbucket-app-password"
			 ],
			 "dockerhub":[
				"docker-access-token"
			 ]
		  }
	   },
	   {
		  "id":"2",
		  "created_at":"2023-02-02T16:05:56Z",
		  "updated_at":"2023-02-02T16:05:56Z",
		  "name":"/insights/platform/cloud-meter",
		  "display_name":"RHEL management",
		  "dependent_applications":[

		  ],
		  "supported_source_types":[
			 "amazon",
			 "azure",
			 "google"
		  ],
		  "supported_authentication_types":{
			 "azure":[
				"lighthouse_subscription_id"
			 ],
			 "amazon":[
				"cloud-meter-arn"
			 ]
		  }
	   },
	   {
		  "id":"3",
		  "created_at":"2023-02-02T16:05:56Z",
		  "updated_at":"2023-02-02T16:05:56Z",
		  "name":"/insights/platform/cost-management",
		  "display_name":"Cost Management",
		  "dependent_applications":[

		  ],
		  "supported_source_types":[
			 "amazon",
			 "azure",
			 "google",
			 "oracle-cloud-infrastructure",
			 "openshift",
			 "ibm"
		  ],
		  "supported_authentication_types":{
			 "ibm":[
				"api_token_account_id"
			 ],
			 "azure":[
				"tenant_id_client_id_client_secret"
			 ],
			 "amazon":[
				"arn"
			 ],
			 "google":[
				"project_id_service_account_json"
			 ],
			 "openshift":[
				"token"
			 ],
			 "oracle-cloud-infrastructure":[
				"ocid"
			 ]
		  }
	   },
	   {
		  "id":"4",
		  "created_at":"2023-02-02T16:05:56Z",
		  "updated_at":"2023-02-02T16:05:56Z",
		  "name":"/insights/platform/fifi",
		  "display_name":"Remediations",
		  "dependent_applications":[

		  ],
		  "supported_source_types":[
			 "satellite"
		  ],
		  "supported_authentication_types":{
			 "satellite":[
				"receptor_node"
			 ]
		  }
	   },
	   {
		  "id":"5",
		  "created_at":"2023-02-02T16:05:56Z",
		  "updated_at":"2023-02-02T16:05:56Z",
		  "name":"/insights/platform/provisioning",
		  "display_name":"Provisioning",
		  "dependent_applications":[

		  ],
		  "supported_source_types":[
			 "amazon",
			 "azure",
			 "google"
		  ],
		  "supported_authentication_types":{
			 "azure":[
				"provisioning_lighthouse_subscription_id"
			 ],
			 "amazon":[
				"provisioning-arn"
			 ],
			 "google":[
				"provisioning_project_id"
			 ]
		  }
	   }
	],
	"meta":{
	   "count":5,
	   "limit":100,
	   "offset":0
	},
	"links":{
	   "first":"/api/sources/v3.1/application_types?limit=100&offset=0",
	   "last":"/api/sources/v3.1/application_types?limit=100&offset=100"
	}
 }
